llama_index/tools/tavily_research/__init__.py
llama_index/tools/tavily_research/base.py
llama_index_tools_tavily_research-0.4.2.dist-info/METADATA
llama_index_tools_tavily_research-0.4.2.dist-info/WHEEL
llama_index_tools_tavily_research-0.4.2.dist-info/licenses/LICENSE
llama_index_tools_tavily_research-0.4.2.dist-info/RECORD
