Metadata-Version: 2.4
Name: llama-index-tools-tavily-research
Version: 0.4.2
Summary: llama-index tools tavily_research integration
Author-email: Your Name <you@example.com>
Maintainer: rotemweiss57
License-Expression: MIT
License-File: LICENSE
Requires-Python: <4.0,>=3.9
Requires-Dist: llama-index-core<0.15,>=0.13.0
Requires-Dist: tavily-python>=0.2.4
